{
    "title": "Winter Outfit #2 | Winter Colors Match: Blue & White | LOOKBOOK",
    "description": "OUTFIT DETAILS\u261f\u261f\u261f - Coat by 19.70 - Hat by Barbisio (styled by me with beads and a feather) - Turtleneck sweater by Hermitage - Jeans by Lee - Chelsea ...",
    "referenceId": "01fkvEuAQlE",
    "date_created": "1496947139",
    "date_modified": "1496947139",
    "tags": null,
    "sourceId": "4",
    "VIDEO_LENGTH": "SHORT",
    "status": "approved",
    "visibility": "1",
    "main_category": null,
    "sub_category": null,
    "VV_VI": null,
    "CVV_VI": null,
    "engagement_score": null,
    "conversion_score": null,
    "id": "97124162",
    "loginId": "1758403",
    "entityType": "1",
    "titleTextEncoded": "Winter-Outfit-2-Winter-Colors-Match-Blue-White-LOOKBOOK",
    "category": null,
    "duration": 209,
    "settings": null,
    "asset": {
        "type": "youtube",
        "author": "The Tomboy's Parlour",
        "hdvFlag": 1,
        "description": "OUTFIT DETAILS\u261f\u261f\u261f - Coat by 19.70 - Hat by Barbisio (styled by me with beads and a feather) - Turtleneck sweater by Hermitage - Jeans by Lee - Chelsea ...",
        "tags": "",
        "thumbnailUrl": "https:\/\/i.ytimg.com\/vi\/01fkvEuAQlE\/hqdefault.jpg",
        "videoId": "01fkvEuAQlE",
        "mediaDuration": 209,
        "prettyDuration": "00:03:29"
    },
    "transcripts": null,
    "metrics_statistics": null,
    "tvp_profiles": null,
    "tvp_profiles_manual": null,
    "tvp_profiles_maxscore": null
}